ok_api/__init__.py
ok_api/ok_api.py
ok_api/ok_exceptions.py
ok_api/ok_upload.py
ok_api-1.0.1.dist-info/LICENSE
ok_api-1.0.1.dist-info/METADATA
ok_api-1.0.1.dist-info/WHEEL
ok_api-1.0.1.dist-info/top_level.txt
ok_api-1.0.1.dist-info/RECORD
